pydecklib/__init__.py
pydecklib/card.py
pydecklib/deck.py
pydecklib-0.1.1.dist-info/LICENSE
pydecklib-0.1.1.dist-info/METADATA
pydecklib-0.1.1.dist-info/WHEEL
pydecklib-0.1.1.dist-info/RECORD
