Metadata-Version: 2.1
Name: pydecklib
Version: 0.1.1
Summary: A deck of cards
License: MIT
Author: amaurylekens
Requires-Python: >=3.9,<4.0
Classifier: License :: OSI Approved :: MIT License
Classifier: Programming Language :: Python :: 3
Classifier: Programming Language :: Python :: 3.9
Classifier: Programming Language :: Python :: 3.10
Classifier: Programming Language :: Python :: 3.11
